hwc_bgrx_8888_ndarray_to_pil_image.py
hwc_bgrx_8888_ndarray_to_pil_image-0.1.0a0.dist-info/licenses/LICENSE
hwc_bgrx_8888_ndarray_to_pil_image-0.1.0a0.dist-info/METADATA
hwc_bgrx_8888_ndarray_to_pil_image-0.1.0a0.dist-info/WHEEL
hwc_bgrx_8888_ndarray_to_pil_image-0.1.0a0.dist-info/top_level.txt
hwc_bgrx_8888_ndarray_to_pil_image-0.1.0a0.dist-info/RECORD
