Metadata-Version: 2.4
Name: hwc-bgrx-8888-ndarray-to-pil-image
Version: 0.1.0a0
Summary: Convert an HWC BGR 888 or BGRX 8888 NumPy ndarray to an HWC RGB 888 PIL.Image, with the alpha/unused channel discarded.
Author-email: Jifeng Wu <jifengwu2k@gmail.com>
License-Expression: MIT
Project-URL: Homepage, https://github.com/jifengwu2k/hwc-bgrx-8888-ndarray-to-pil-image
Project-URL: Bug Tracker, https://github.com/jifengwu2k/hwc-bgrx-8888-ndarray-to-pil-image/issues
Classifier: Programming Language :: Python :: 2
Classifier: Programming Language :: Python :: 3
Classifier: Operating System :: OS Independent
Requires-Python: >=2
License-File: LICENSE
Requires-Dist: numpy
Requires-Dist: pillow
Dynamic: license-file
